[
    {
        "jmhVersion" : "1.24",
        "benchmark" : "cn.zlb.jmh.StringConnectTest.testStringAdd",
        "mode" : "thrpt",
        "threads" : 2,
        "forks" : 1,
        "jvm" : "/Library/Java/JavaVirtualMachines/jdk1.8.0_231.jdk/Contents/Home/jre/bin/java",
        "jvmArgs" : [
            "-javaagent:/Applications/IntelliJ IDEA.app/Contents/lib/idea_rt.jar=64586:/Applications/IntelliJ IDEA.app/Contents/bin",
            "-Dfile.encoding=UTF-8"
        ],
        "jdkVersion" : "1.8.0_231",
        "vmName" : "Java HotSpot(TM) 64-Bit Server VM",
        "vmVersion" : "25.231-b11",
        "warmupIterations" : 2,
        "warmupTime" : "1 s",
        "warmupBatchSize" : 1,
        "measurementIterations" : 2,
        "measurementTime" : "1 s",
        "measurementBatchSize" : 1,
        "params" : {
            "length" : "10"
        },
        "primaryMetric" : {
            "score" : 0.0036376393915803712,
            "scoreError" : "NaN",
            "scoreConfidence" : [
                "NaN",
                "NaN"
            ],
            "scorePercentiles" : {
                "0.0" : 0.0030703071675190147,
                "50.0" : 0.0036376393915803712,
                "90.0" : 0.004204971615641728,
                "95.0" : 0.004204971615641728,
                "99.0" : 0.004204971615641728,
                "99.9" : 0.004204971615641728,
                "99.99" : 0.004204971615641728,
                "99.999" : 0.004204971615641728,
                "99.9999" : 0.004204971615641728,
                "100.0" : 0.004204971615641728
            },
            "scoreUnit" : "ops/ns",
            "rawData" : [
                [
                    0.0030703071675190147,
                    0.004204971615641728
                ]
            ]
        },
        "secondaryMetrics" : {
        }
    },
    {
        "jmhVersion" : "1.24",
        "benchmark" : "cn.zlb.jmh.StringConnectTest.testStringAdd",
        "mode" : "thrpt",
        "threads" : 2,
        "forks" : 1,
        "jvm" : "/Library/Java/JavaVirtualMachines/jdk1.8.0_231.jdk/Contents/Home/jre/bin/java",
        "jvmArgs" : [
            "-javaagent:/Applications/IntelliJ IDEA.app/Contents/lib/idea_rt.jar=64586:/Applications/IntelliJ IDEA.app/Contents/bin",
            "-Dfile.encoding=UTF-8"
        ],
        "jdkVersion" : "1.8.0_231",
        "vmName" : "Java HotSpot(TM) 64-Bit Server VM",
        "vmVersion" : "25.231-b11",
        "warmupIterations" : 2,
        "warmupTime" : "1 s",
        "warmupBatchSize" : 1,
        "measurementIterations" : 2,
        "measurementTime" : "1 s",
        "measurementBatchSize" : 1,
        "params" : {
            "length" : "50"
        },
        "primaryMetric" : {
            "score" : 0.0011407825359115212,
            "scoreError" : "NaN",
            "scoreConfidence" : [
                "NaN",
                "NaN"
            ],
            "scorePercentiles" : {
                "0.0" : 0.0010265636582637739,
                "50.0" : 0.0011407825359115212,
                "90.0" : 0.0012550014135592684,
                "95.0" : 0.0012550014135592684,
                "99.0" : 0.0012550014135592684,
                "99.9" : 0.0012550014135592684,
                "99.99" : 0.0012550014135592684,
                "99.999" : 0.0012550014135592684,
                "99.9999" : 0.0012550014135592684,
                "100.0" : 0.0012550014135592684
            },
            "scoreUnit" : "ops/ns",
            "rawData" : [
                [
                    0.0010265636582637739,
                    0.0012550014135592684
                ]
            ]
        },
        "secondaryMetrics" : {
        }
    },
    {
        "jmhVersion" : "1.24",
        "benchmark" : "cn.zlb.jmh.StringConnectTest.testStringBuilderAdd",
        "mode" : "thrpt",
        "threads" : 2,
        "forks" : 1,
        "jvm" : "/Library/Java/JavaVirtualMachines/jdk1.8.0_231.jdk/Contents/Home/jre/bin/java",
        "jvmArgs" : [
            "-javaagent:/Applications/IntelliJ IDEA.app/Contents/lib/idea_rt.jar=64586:/Applications/IntelliJ IDEA.app/Contents/bin",
            "-Dfile.encoding=UTF-8"
        ],
        "jdkVersion" : "1.8.0_231",
        "vmName" : "Java HotSpot(TM) 64-Bit Server VM",
        "vmVersion" : "25.231-b11",
        "warmupIterations" : 2,
        "warmupTime" : "1 s",
        "warmupBatchSize" : 1,
        "measurementIterations" : 2,
        "measurementTime" : "1 s",
        "measurementBatchSize" : 1,
        "params" : {
            "length" : "10"
        },
        "primaryMetric" : {
            "score" : 0.013218537107683712,
            "scoreError" : "NaN",
            "scoreConfidence" : [
                "NaN",
                "NaN"
            ],
            "scorePercentiles" : {
                "0.0" : 0.01161111141120895,
                "50.0" : 0.013218537107683712,
                "90.0" : 0.014825962804158474,
                "95.0" : 0.014825962804158474,
                "99.0" : 0.014825962804158474,
                "99.9" : 0.014825962804158474,
                "99.99" : 0.014825962804158474,
                "99.999" : 0.014825962804158474,
                "99.9999" : 0.014825962804158474,
                "100.0" : 0.014825962804158474
            },
            "scoreUnit" : "ops/ns",
            "rawData" : [
                [
                    0.014825962804158474,
                    0.01161111141120895
                ]
            ]
        },
        "secondaryMetrics" : {
        }
    },
    {
        "jmhVersion" : "1.24",
        "benchmark" : "cn.zlb.jmh.StringConnectTest.testStringBuilderAdd",
        "mode" : "thrpt",
        "threads" : 2,
        "forks" : 1,
        "jvm" : "/Library/Java/JavaVirtualMachines/jdk1.8.0_231.jdk/Contents/Home/jre/bin/java",
        "jvmArgs" : [
            "-javaagent:/Applications/IntelliJ IDEA.app/Contents/lib/idea_rt.jar=64586:/Applications/IntelliJ IDEA.app/Contents/bin",
            "-Dfile.encoding=UTF-8"
        ],
        "jdkVersion" : "1.8.0_231",
        "vmName" : "Java HotSpot(TM) 64-Bit Server VM",
        "vmVersion" : "25.231-b11",
        "warmupIterations" : 2,
        "warmupTime" : "1 s",
        "warmupBatchSize" : 1,
        "measurementIterations" : 2,
        "measurementTime" : "1 s",
        "measurementBatchSize" : 1,
        "params" : {
            "length" : "50"
        },
        "primaryMetric" : {
            "score" : 0.002184468203712739,
            "scoreError" : "NaN",
            "scoreConfidence" : [
                "NaN",
                "NaN"
            ],
            "scorePercentiles" : {
                "0.0" : 0.002072466169474591,
                "50.0" : 0.002184468203712739,
                "90.0" : 0.0022964702379508874,
                "95.0" : 0.0022964702379508874,
                "99.0" : 0.0022964702379508874,
                "99.9" : 0.0022964702379508874,
                "99.99" : 0.0022964702379508874,
                "99.999" : 0.0022964702379508874,
                "99.9999" : 0.0022964702379508874,
                "100.0" : 0.0022964702379508874
            },
            "scoreUnit" : "ops/ns",
            "rawData" : [
                [
                    0.0022964702379508874,
                    0.002072466169474591
                ]
            ]
        },
        "secondaryMetrics" : {
        }
    },
    {
        "jmhVersion" : "1.24",
        "benchmark" : "cn.zlb.jmh.StringConnectTest.testStringAdd",
        "mode" : "avgt",
        "threads" : 2,
        "forks" : 1,
        "jvm" : "/Library/Java/JavaVirtualMachines/jdk1.8.0_231.jdk/Contents/Home/jre/bin/java",
        "jvmArgs" : [
            "-javaagent:/Applications/IntelliJ IDEA.app/Contents/lib/idea_rt.jar=64586:/Applications/IntelliJ IDEA.app/Contents/bin",
            "-Dfile.encoding=UTF-8"
        ],
        "jdkVersion" : "1.8.0_231",
        "vmName" : "Java HotSpot(TM) 64-Bit Server VM",
        "vmVersion" : "25.231-b11",
        "warmupIterations" : 2,
        "warmupTime" : "1 s",
        "warmupBatchSize" : 1,
        "measurementIterations" : 2,
        "measurementTime" : "1 s",
        "measurementBatchSize" : 1,
        "params" : {
            "length" : "10"
        },
        "primaryMetric" : {
            "score" : 251.26698045509966,
            "scoreError" : "NaN",
            "scoreConfidence" : [
                "NaN",
                "NaN"
            ],
            "scorePercentiles" : {
                "0.0" : 247.54177609777702,
                "50.0" : 251.26698045509966,
                "90.0" : 254.9921848124223,
                "95.0" : 254.9921848124223,
                "99.0" : 254.9921848124223,
                "99.9" : 254.9921848124223,
                "99.99" : 254.9921848124223,
                "99.999" : 254.9921848124223,
                "99.9999" : 254.9921848124223,
                "100.0" : 254.9921848124223
            },
            "scoreUnit" : "ns/op",
            "rawData" : [
                [
                    247.54177609777702,
                    254.9921848124223
                ]
            ]
        },
        "secondaryMetrics" : {
        }
    },
    {
        "jmhVersion" : "1.24",
        "benchmark" : "cn.zlb.jmh.StringConnectTest.testStringAdd",
        "mode" : "avgt",
        "threads" : 2,
        "forks" : 1,
        "jvm" : "/Library/Java/JavaVirtualMachines/jdk1.8.0_231.jdk/Contents/Home/jre/bin/java",
        "jvmArgs" : [
            "-javaagent:/Applications/IntelliJ IDEA.app/Contents/lib/idea_rt.jar=64586:/Applications/IntelliJ IDEA.app/Contents/bin",
            "-Dfile.encoding=UTF-8"
        ],
        "jdkVersion" : "1.8.0_231",
        "vmName" : "Java HotSpot(TM) 64-Bit Server VM",
        "vmVersion" : "25.231-b11",
        "warmupIterations" : 2,
        "warmupTime" : "1 s",
        "warmupBatchSize" : 1,
        "measurementIterations" : 2,
        "measurementTime" : "1 s",
        "measurementBatchSize" : 1,
        "params" : {
            "length" : "50"
        },
        "primaryMetric" : {
            "score" : 2241.3427475345416,
            "scoreError" : "NaN",
            "scoreConfidence" : [
                "NaN",
                "NaN"
            ],
            "scorePercentiles" : {
                "0.0" : 1654.3264659918136,
                "50.0" : 2241.3427475345416,
                "90.0" : 2828.35902907727,
                "95.0" : 2828.35902907727,
                "99.0" : 2828.35902907727,
                "99.9" : 2828.35902907727,
                "99.99" : 2828.35902907727,
                "99.999" : 2828.35902907727,
                "99.9999" : 2828.35902907727,
                "100.0" : 2828.35902907727
            },
            "scoreUnit" : "ns/op",
            "rawData" : [
                [
                    1654.3264659918136,
                    2828.35902907727
                ]
            ]
        },
        "secondaryMetrics" : {
        }
    },
    {
        "jmhVersion" : "1.24",
        "benchmark" : "cn.zlb.jmh.StringConnectTest.testStringBuilderAdd",
        "mode" : "avgt",
        "threads" : 2,
        "forks" : 1,
        "jvm" : "/Library/Java/JavaVirtualMachines/jdk1.8.0_231.jdk/Contents/Home/jre/bin/java",
        "jvmArgs" : [
            "-javaagent:/Applications/IntelliJ IDEA.app/Contents/lib/idea_rt.jar=64586:/Applications/IntelliJ IDEA.app/Contents/bin",
            "-Dfile.encoding=UTF-8"
        ],
        "jdkVersion" : "1.8.0_231",
        "vmName" : "Java HotSpot(TM) 64-Bit Server VM",
        "vmVersion" : "25.231-b11",
        "warmupIterations" : 2,
        "warmupTime" : "1 s",
        "warmupBatchSize" : 1,
        "measurementIterations" : 2,
        "measurementTime" : "1 s",
        "measurementBatchSize" : 1,
        "params" : {
            "length" : "10"
        },
        "primaryMetric" : {
            "score" : 125.01723007669305,
            "scoreError" : "NaN",
            "scoreConfidence" : [
                "NaN",
                "NaN"
            ],
            "scorePercentiles" : {
                "0.0" : 122.45708382800046,
                "50.0" : 125.01723007669305,
                "90.0" : 127.57737632538564,
                "95.0" : 127.57737632538564,
                "99.0" : 127.57737632538564,
                "99.9" : 127.57737632538564,
                "99.99" : 127.57737632538564,
                "99.999" : 127.57737632538564,
                "99.9999" : 127.57737632538564,
                "100.0" : 127.57737632538564
            },
            "scoreUnit" : "ns/op",
            "rawData" : [
                [
                    127.57737632538564,
                    122.45708382800046
                ]
            ]
        },
        "secondaryMetrics" : {
        }
    },
    {
        "jmhVersion" : "1.24",
        "benchmark" : "cn.zlb.jmh.StringConnectTest.testStringBuilderAdd",
        "mode" : "avgt",
        "threads" : 2,
        "forks" : 1,
        "jvm" : "/Library/Java/JavaVirtualMachines/jdk1.8.0_231.jdk/Contents/Home/jre/bin/java",
        "jvmArgs" : [
            "-javaagent:/Applications/IntelliJ IDEA.app/Contents/lib/idea_rt.jar=64586:/Applications/IntelliJ IDEA.app/Contents/bin",
            "-Dfile.encoding=UTF-8"
        ],
        "jdkVersion" : "1.8.0_231",
        "vmName" : "Java HotSpot(TM) 64-Bit Server VM",
        "vmVersion" : "25.231-b11",
        "warmupIterations" : 2,
        "warmupTime" : "1 s",
        "warmupBatchSize" : 1,
        "measurementIterations" : 2,
        "measurementTime" : "1 s",
        "measurementBatchSize" : 1,
        "params" : {
            "length" : "50"
        },
        "primaryMetric" : {
            "score" : 838.4993111971935,
            "scoreError" : "NaN",
            "scoreConfidence" : [
                "NaN",
                "NaN"
            ],
            "scorePercentiles" : {
                "0.0" : 831.4154433211856,
                "50.0" : 838.4993111971935,
                "90.0" : 845.5831790732013,
                "95.0" : 845.5831790732013,
                "99.0" : 845.5831790732013,
                "99.9" : 845.5831790732013,
                "99.99" : 845.5831790732013,
                "99.999" : 845.5831790732013,
                "99.9999" : 845.5831790732013,
                "100.0" : 845.5831790732013
            },
            "scoreUnit" : "ns/op",
            "rawData" : [
                [
                    831.4154433211856,
                    845.5831790732013
                ]
            ]
        },
        "secondaryMetrics" : {
        }
    }
]


